immutable_namespace.py
setup.py
immutable_namespace.egg-info/PKG-INFO
immutable_namespace.egg-info/SOURCES.txt
immutable_namespace.egg-info/dependency_links.txt
immutable_namespace.egg-info/top_level.txt