Metadata-Version: 1.0
Name: immutable-namespace
Version: 0.1
Summary: immutable namespace for python
Home-page: UNKNOWN
Author: Jayme Bird
Author-email: jayme.cbird@gmail.com
License: UNKNOWN
Keywords: immutable,namespace
Platform: UNKNOWN
